{
  "unpublishedPage": {
    "name": "Page1",
    "slug": "page1",
    "layouts": [
      {
        "viewMode": false,
        "dsl": {
          "widgetName": "MainContainer",
          "backgroundColor": "none",
          "rightColumn": 4896,
          "snapColumns": 64,
          "detachFromLayout": true,
          "widgetId": "0",
          "topRow": 0,
          "bottomRow": 1292,
          "containerStyle": "none",
          "snapRows": 125,
          "parentRowSpace": 1,
          "type": "CANVAS_WIDGET",
          "canExtend": true,
          "version": 71,
          "minHeight": 1292,
          "dynamicTriggerPathList": [],
          "parentColumnSpace": 1,
          "dynamicBindingPathList": [],
          "leftColumn": 0,
          "children": [
            {
              "schema": "{\"form\":{\"labelCol\":6,\"wrapperCol\":12},\"schema\":{\"type\":\"object\",\"properties\":{\"rpw25nx0rp2\":{\"type\":\"string\",\"title\":\"Input\",\"x-decorator\":\"FormItem\",\"x-component\":\"Input\",\"x-validator\":[],\"x-component-props\":{},\"x-decorator-props\":{},\"x-designable-id\":\"rpw25nx0rp2\",\"x-index\":0},\"fx3t04gv848\":{\"type\":\"number\",\"title\":\"NumberPicker\",\"x-decorator\":\"FormItem\",\"x-component\":\"NumberPicker\",\"x-validator\":[],\"x-component-props\":{},\"x-decorator-props\":{},\"x-designable-id\":\"fx3t04gv848\",\"x-index\":1},\"mocckwgd6x0\":{\"type\":\"string\",\"title\":\"Input\",\"x-decorator\":\"FormItem\",\"x-component\":\"Input\",\"x-validator\":[],\"x-component-props\":{},\"x-decorator-props\":{},\"x-designable-id\":\"mocckwgd6x0\",\"x-index\":2},\"v7bkkubg3ia\":{\"type\":\"string\",\"title\":\"TextArea\",\"x-decorator\":\"FormItem\",\"x-component\":\"Input.TextArea\",\"x-validator\":[],\"x-component-props\":{},\"x-decorator-props\":{},\"x-designable-id\":\"v7bkkubg3ia\",\"x-index\":3},\"4xvwagtuldb\":{\"title\":\"Cascader\",\"x-decorator\":\"FormItem\",\"x-component\":\"Cascader\",\"x-validator\":[],\"x-component-props\":{},\"x-decorator-props\":{},\"x-designable-id\":\"4xvwagtuldb\",\"x-index\":4},\"buv1o4pwqu8\":{\"title\":\"TreeSelect\",\"x-decorator\":\"FormItem\",\"x-component\":\"TreeSelect\",\"x-validator\":[],\"x-component-props\":{},\"x-decorator-props\":{},\"x-designable-id\":\"buv1o4pwqu8\",\"x-index\":5},\"3vzgb2y0oku\":{\"title\":\"Transfer\",\"x-decorator\":\"FormItem\",\"x-component\":\"Transfer\",\"x-validator\":[],\"x-component-props\":{},\"x-decorator-props\":{},\"x-designable-id\":\"3vzgb2y0oku\",\"x-index\":6}},\"x-designable-id\":\"r1gyr7u8fq5\"}}",
              "widgetName": "formily1",
              "isCanvas": false,
              "displayName": "Formily表单",
              "iconSVG": "/static/media/icon.ea3e08d130e59c56867ae40114c10eed.svg",
              "searchTags": [
                "form",
                "submit"
              ],
              "topRow": 8,
              "bottomRow": 56,
              "parentRowSpace": 10,
              "title": "表单标题",
              "type": "FORMILY_WIDGET",
              "triggerLabel": "打开表单",
              "hideCard": false,
              "parentColumnSpace": 17.9375,
              "dynamicTriggerPathList": [],
              "leftColumn": 9,
              "dynamicBindingPathList": [],
              "resetLabel": "重置",
              "showReset": true,
              "key": "k6n0ix04aq",
              "submitLabel": "提交",
              "formType": "PLAIN",
              "isDeprecated": false,
              "rightColumn": 41,
              "widgetId": "c2kl6l964w",
              "isVisible": true,
              "version": 1,
              "parentId": "0",
              "renderMode": "CANVAS",
              "isLoading": false
            }
          ]
        },
        "layoutOnLoadActions": [],
        "layoutOnLoadActionErrors": [],
        "validOnPageLoadActions": true,
        "id": "Page1",
        "deleted": false,
        "policies": [],
        "userPermissions": []
      }
    ],
    "userPermissions": [],
    "policies": []
  },
  "deleted": false,
  "gitSyncId": "6459a0a6de5d5825c7ae593e_6459a0a6de5d5825c7ae5940"
}